pyruckus/RuckusSSH.py
pyruckus/__init__.py
pyruckus/const.py
pyruckus/exceptions.py
pyruckus/response_parser.py
pyruckus-0.16.dist-info/LICENSE
pyruckus-0.16.dist-info/METADATA
pyruckus-0.16.dist-info/WHEEL
pyruckus-0.16.dist-info/top_level.txt
pyruckus-0.16.dist-info/zip-safe
pyruckus-0.16.dist-info/RECORD
