Metadata-Version: 2.1
Name: pyruckus
Version: 0.16
Summary: Python API to interact with a Ruckus Unleashed device.
Home-page: https://github.com/gabe565/pyruckus
Author: Gabe Cook
Author-email: gabe565@gmail.com
License: MIT
Platform: UNKNOWN
Requires-Python: >=3.6
License-File: LICENSE
Requires-Dist: pexpect (>=4.0)
Requires-Dist: python-slugify (>=4.0.1)
